[
    {
        "testsuite" : "Test get sensing values",
        "testcases" :   [
            {
                "name"              : "listdevices",
                "description"       : "Get list of available devices in the controller",
                "input"             : {
                    "devicetype"    : "zwave" 
                }
            },

            {
                "name"              : "elect_getting",
                "description"       : "Get status of ELEC (electrical load value for watt and KWH) for verifying value which is available",
                "input"             : {
                    "devicetype"    : "zwave",
                    "id"            : "D_ID",
                    "class"         : "METER",
                    "readcommand"   : "GET",
                    "type"          : "ELEC",
                    "force"         : "1"
                },
                "verdict"       : {
                    "method"        : "reference",
                    "value"     : {
                           "unit": "ref",
                           "time": "ref",
                           "electricmeter": "ref"
                    }
                }
            },

            {
                "name"              : "get_temperature",
                "description"       : "Get status of TEMP ( temperature in fahrenheit and celsius ) for verifying value which is available",
                "input"             : {
                    "devicetype"    : "zwave",
                    "id"            : "D_ID",
                    "class"         : "SENSOR_MULTILEVEL",
                    "readcommand"   : "GET",
                    "type"          : "TEMP",
                    "force"         : "1"
                },
                "verdict"       : {
                    "method"        : "reference",
                    "value"     : {
                        "fahrenheit"    : "ref",
                        "celsius"       : "ref"
                    }
                }
            }
        ]
    },

    {
        "testsuite" : "Test association with another device",
        "testcases" : [
            {
                "name"              : "basic_set_association",
                "description"       : "Association with our controller (ceres)",
                "input"             : {
                    "devicetype"    : "zwave",
                    "id"            : "D_ID",
                    "class"         : "ASSOCIATION",
                    "writecommand"  : "SET",
                    "readcommand"   : "GET",
                    "data0"         : "REPORT_GROUP",
                    "data1"         : "01",
                    "data2"         : "1",
                    "type"          : "REPORT_GROUP",
                    "force"         : "1"
                },
                "verdict"       : {
                    "method"        : "expectation",
                    "value"     : {
                        "nodefollow"    : ["01"]
                    }
                }
            },

            {
                "name"              : "basic_set_association",
                "description"       : "Association with smart dimmer zwave device",
                "input"             : {
                    "devicetype"    : "zwave",
                    "id"            : "D_ID",
                    "class"         : "ASSOCIATION",
                    "writecommand"  : "SET",
                    "readcommand"   : "GET",
                    "data0"         : "ONOFF_GROUP",
                    "data1"         : "6F",
                    "data2"         : "1",
                    "type"          : "ONOFF_GROUP",
                    "force"         : "1"
                },
                "verdict"       : {
                    "method"        : "expectation",
                    "value"     : {
                        "nodefollow"    : ["6F"]
                    }
                }
            },

            {
                "name"              : "basic_set_association",
                "description"       : "Association with smart Led zwave device",
                "input"             : {
                    "devicetype"    : "zwave",
                    "id"            : "D_ID",
                    "class"         : "ASSOCIATION",
                    "writecommand"  : "SET",
                    "readcommand"   : "GET",
                    "data0"         : "ONOFF_GROUP",
                    "data1"         : "6B",
                    "data2"         : "1",
                    "type"          : "ONOFF_GROUP",
                    "force"         : "1"
                },
                "verdict"       : {
                    "method"        : "expectation",
                    "value"     : {
                        "nodefollow"    : ["6B"]
                    }
                }
            },

            {
                "name"              : "lock_configuration",
                "description"       : "Set LOCK_CONFIGURATION is 0, value 0 means disable lock notification",
                "input"             : {
                    "devicetype"    : "zwave",
                    "id"            : "D_ID",
                    "class"         : "CONFIGURATION",
                    "writecommand"  : "SET",
                    "readcommand"   : "GET",
                    "data0"         : "LOCK_CONFIGURATION",
                    "data1"         : "0",
                    "data2"         : "1",
                    "type"          : "LOCK_CONFIGURATION",
                    "force"         : "1"
                },
                "verdict"       : {
                    "method"        : "expectation",
                    "value"     : {
                        "value" :     0
                    }
                }
            },

            {
                "name"              : "noti_send_configuration",
                "description"       : "Set NOTIFICATION is 2, value 2 means enable sending basic CC report notification to our controller whwen the state of Siren changed",
                "input"             : {
                    "devicetype"    : "zwave",
                    "id"            : "D_ID",
                    "class"         : "CONFIGURATION",
                    "writecommand"  : "SET",
                    "readcommand"   : "GET",
                    "data0"         : "NOTIFICATION",
                    "data1"         : "2",
                    "data2"         : "1",
                    "type"          : "NOTIFICATION",
                    "force"         : "1"
                },
                "verdict"       : {
                    "method"        : "expectation",
                    "value"     : {
                        "value" :     2
                    }
                }
            },

            {
                "name"              : "physical_test",
                "description"       : "Wait 60s to test association",
                "input"             : {
                    "devicetype"    : "zwave",
                    "id"            : "D_ID",
                    "time"          : "60"
                }
            }
        ]
    },

    {
        "testsuite" : "Test lock configuration",
        "testcases" : [
            {
                "name"              : "lock_configuration",
                "description"       : "Set LOCK_CONFIGURATION is 1, value 1 means enable lock notification",
                "input"             : {
                    "devicetype"    : "zwave",
                    "id"            : "D_ID",
                    "class"         : "CONFIGURATION",
                    "writecommand"  : "SET",
                    "readcommand"   : "GET",
                    "data0"         : "LOCK_CONFIGURATION",
                    "data1"         : "1",
                    "data2"         : "1",
                    "type"          : "LOCK_CONFIGURATION",
                    "force"         : "1"
                },
                "verdict"       : {
                    "method"        : "expectation",
                    "value"     : {
                        "value" :     1
                    }
                }
            },

             {
                "name"              : "noti_send_configuration",
                "description"       : "This test case use to test lock configuration, expectation is failed",
                "input"             : {
                    "devicetype"    : "zwave",
                    "id"            : "D_ID",
                    "class"         : "CONFIGURATION",
                    "writecommand"  : "SET",
                    "readcommand"   : "GET",
                    "data0"         : "NOTIFICATION",
                    "data1"         : "1",
                    "data2"         : "1",
                    "type"          : "NOTIFICATION",
                    "force"         : "1"
                },
                "verdict"       : {
                    "method"        : "expectation",
                    "value"     : {
                        "value" :     1
                    }
                }
            }
        ]
    },

    {
        "testsuite" : "Test overload protection configuration",
        "testcases" : [
            {
                "name"              : "lock_configuration",
                "description"       : "Set LOCK_CONFIGURATION is 0, value 0 means disable lock notification",
                "input"             : {
                    "devicetype"    : "zwave",
                    "id"            : "D_ID",
                    "class"         : "CONFIGURATION",
                    "writecommand"  : "SET",
                    "readcommand"   : "GET",
                    "data0"         : "LOCK_CONFIGURATION",
                    "data1"         : "0",
                    "data2"         : "1",
                    "type"          : "LOCK_CONFIGURATION",
                    "force"         : "1"
                },
                "verdict"       : {
                    "method"        : "expectation",
                    "value"     : {
                        "value" :     0
                    }
                }
            },

            {
                "name"              : "controlonoff",
                "description"       : "Value 30 (Hex) means Smart dimmer will dim with value 48",
                "input"             : {
                    "devicetype"    : "zwave",
                    "id"            : "D_ID",
                    "value"         : "30"
                },
                "verdict"       : {
                    "method"        : "expectation",
                    "value"     : {
                        "value" :  30
                    }
                }
            },

            {
                "name"              : "overload_protect",
                "description"       : "Set value 0 for OVERLOAD_PROTECT, value 0 means disable Current overload protection",
                "input"             : {
                    "devicetype"    : "zwave",
                    "id"            : "D_ID",
                    "class"         : "CONFIGURATION",
                    "writecommand"  : "SET",
                    "readcommand"   : "GET",
                    "data0"         : "OVERLOAD_PROTECT",
                    "data1"         : "0",
                    "data2"         : "1",
                    "type"          : "OVERLOAD_PROTECT",
                    "force"         : "1"
                },
                "verdict"       : {
                    "method"        : "expectation",
                    "value"     : {
                        "value" :     0
                    }
                }
            },

            {
                "name"              : "physical_test",
                "description"       : "Wait for 60s to test overload protection, The load wont be closed when the Current is more than 15.5A and the time is more than 2 minutes. ",
                "input"             : {
                    "devicetype"    : "zwave",
                    "id"            : "D_ID",
                    "time"          : "60"
                }
            },

            {
                "name"              : "controlonoff",
                "description"       : "Turn off device",
                "input"             : {
                    "devicetype"    : "zwave",
                    "id"            : "D_ID",
                    "value"         : "0"
                },
                "verdict"       : {
                    "method"        : "expectation",
                    "value"     : {
                        "value" :  0
                    }
                }
            },

            {
                "name"              : "controlonoff",
                "description"       : "Value 30 (Hex) means Smart dimmer will dim with value 48",
                "input"             : {
                    "devicetype"    : "zwave",
                    "id"            : "D_ID",
                    "value"         : "30"
                },
                "verdict"       : {
                    "method"        : "expectation",
                    "value"     : {
                        "value" :  30
                    }
                }
            },

            {
                "name"              : "overload_protect",
                "description"       : "Set value 1 for OVERLOAD_PROTECT, value 1 means enable Current overload protection",
                "input"             : {
                    "devicetype"    : "zwave",
                    "id"            : "D_ID",
                    "class"         : "CONFIGURATION",
                    "writecommand"  : "SET",
                    "readcommand"   : "GET",
                    "data0"         : "OVERLOAD_PROTECT",
                    "data1"         : "1",
                    "data2"         : "1",
                    "type"          : "OVERLOAD_PROTECT",
                    "force"         : "1"
                },
                "verdict"       : {
                    "method"        : "expectation",
                    "value"     : {
                        "value" :     1
                    }
                }
            },

            {
                "name"              : "physical_test",
                "description"       : "Wait for 60s to test overload protection, The load will be closed when the Current is more than 39.5A and the time is more than 5 seconds. ",
                "input"             : {
                    "devicetype"    : "zwave",
                    "id"            : "D_ID",
                    "time"          : "60"
                }
            },

            {
                "name"              : "controlonoff",
                "description"       : "Turn off device",
                "input"             : {
                    "devicetype"    : "zwave",
                    "id"            : "D_ID",
                    "value"         : "0"
                },
                "verdict"       : {
                    "method"        : "expectation",
                    "value"     : {
                        "value" :  0
                    }
                }
            }
        ]
    },


    {
        "testsuite" : "Test notification sending and Switch multi level configuration",
        "testcases" : [
             {
                "name"              : "noti_send_configuration",
                "description"       : "Set NOTIFICATION is 0, value 0 means disable sending notification to our controller whwen the the load changed",
                "input"             : {
                    "devicetype"    : "zwave",
                    "id"            : "D_ID",
                    "class"         : "CONFIGURATION",
                    "writecommand"  : "SET",
                    "readcommand"   : "GET",
                    "data0"         : "NOTIFICATION",
                    "data1"         : "0",
                    "data2"         : "1",
                    "type"          : "NOTIFICATION",
                    "force"         : "1"
                },
                "verdict"       : {
                    "method"        : "expectation",
                    "value"     : {
                        "value" :     0
                    }
                }
            },

            {
                "name"              : "controlonoff",
                "description"       : "Value 30 (Hex) means Smart dimmer will dim with value 48 and obverse notification send to controller",
                "input"             : {
                    "devicetype"    : "zwave",
                    "id"            : "D_ID",
                    "value"         : "30"
                },
                "verdict"       : {
                    "method"        : "expectation",
                    "value"     : {
                        "value" :  30
                    }
                }
            },

            {
                "name"              : "noti_send_configuration",
                "description"       : "Set NOTIFICATION is 1, value 1 means enable sending hail CC notification to our controller whwen the load changed",
                "input"             : {
                    "devicetype"    : "zwave",
                    "id"            : "D_ID",
                    "class"         : "CONFIGURATION",
                    "writecommand"  : "SET",
                    "readcommand"   : "GET",
                    "data0"         : "NOTIFICATION",
                    "data1"         : "1",
                    "data2"         : "1",
                    "type"          : "NOTIFICATION",
                    "force"         : "1"
                },
                "verdict"       : {
                    "method"        : "expectation",
                    "value"     : {
                        "value" :     1
                    }
                }
            },

            {
                "name"              : "controlonoff",
                "description"       : "Value 63 (Hex) means Smart dimmer will dim with value 99 and obverse notification send to controller",
                "input"             : {
                    "devicetype"    : "zwave",
                    "id"            : "D_ID",
                    "value"         : "63"
                },
                "verdict"       : {
                    "method"        : "expectation",
                    "value"     : {
                        "value" :  63
                    }
                }
            },

            {
                "name"              : "noti_send_configuration",
                "description"       : "Set NOTIFICATION is 2, value 2 means enable sending basic CC report notification to our controller whwen the load changed",
                "input"             : {
                    "devicetype"    : "zwave",
                    "id"            : "D_ID",
                    "class"         : "CONFIGURATION",
                    "writecommand"  : "SET",
                    "readcommand"   : "GET",
                    "data0"         : "NOTIFICATION",
                    "data1"         : "2",
                    "data2"         : "1",
                    "type"          : "NOTIFICATION",
                    "force"         : "1"
                },
                "verdict"       : {
                    "method"        : "expectation",
                    "value"     : {
                        "value" :     2
                    }
                }
            },

            {
                "name"              : "controlonoff",
                "description"       : "Turn off device and obverse notification send to controller",
                "input"             : {
                    "devicetype"    : "zwave",
                    "id"            : "D_ID",
                    "value"         : "0"
                },
                "verdict"       : {
                    "method"        : "expectation",
                    "value"     : {
                        "value" :  0
                    }
                }
            }
        ]
    },

    {
        "testsuite" : "Remove association information",
        "testcases" : [
            {
                "name"              : "remove_association",
                "description"       : "Remove controller (ceres) of REPORT_GROUP",
                "input"             : {
                    "devicetype"    : "zwave",
                    "id"            : "D_ID",
                    "class"         : "ASSOCIATION",
                    "writecommand"  : "REMOVE",
                    "readcommand"   : "GET",
                    "data0"         : "REPORT_GROUP",
                    "data1"         : "01",
                    "data2"         : "1",
                    "type"          : "REPORT_GROUP",
                    "force"         : "1"
                },
                "verdict"       : {
                    "method"        : "expectation",
                    "value"     : {
                        "nodefollow"    : ["01"]
                    }
                }
            },

            {
                "name"              : "remove_association",
                "description"       : "Remove led zwave out of ONOFF_GROUP",
                "input"             : {
                    "devicetype"    : "zwave",
                    "id"            : "D_ID",
                    "class"         : "ASSOCIATION",
                    "writecommand"  : "REMOVE",
                    "readcommand"   : "GET",
                    "data0"         : "ONOFF_GROUP",
                    "data1"         : "6B",
                    "data2"         : "1",
                    "type"          : "ONOFF_GROUP",
                    "force"         : "1"
                },
                "verdict"       : {
                    "method"        : "expectation",
                    "value"     : {
                        "nodefollow"    : ["6B"]
                    }
                }
            },

            {
                "name"              : "remove_association",
                "description"       : "Remove dimmer device zwave out of ONOFF_GROUP",
                "input"             : {
                    "devicetype"    : "zwave",
                    "id"            : "D_ID",
                    "class"         : "ASSOCIATION",
                    "writecommand"  : "REMOVE",
                    "readcommand"   : "GET",
                    "data0"         : "ONOFF_GROUP",
                    "data1"         : "6F",
                    "data2"         : "1",
                    "type"          : "ONOFF_GROUP",
                    "force"         : "1"
                },
                "verdict"       : {
                    "method"        : "expectation",
                    "value"     : {
                        "nodefollow"    : ["6F"]
                    }
                }
            }
        ]
    }
]