[ 
	{
		"testsuit" : "GE Dimmer Switch",
		"serviceid" : "93c06771-c725-48c2-b1ff-5c313ee312cc",
		"testcases" :	[
			{	
				"name"	: "listdevices",
				"input" :{
					"devicetype"	: "zwave"
				}
			},
			{
				"name" : "readspec",
				"input" : {
					"devicetype" 	: "zwave",
					"id" 			: "ID 0",
					"class"			: "CONFIGURATION",
					"command"		: "GET",
					"type"			: "ONOFF_LED"
				}
			},
			{
				"name" : "writespec",
				"input" : {
					"devicetype" 	: "zwave",
					"id" 			: "ID 0",
					"class"			: "CONFIGURATION",
					"command"		: "SET",
					"data0"			: "ONOFF_LED",
					"data1"			: "0",
					"data2"			: ""
				}
			},
			{
				"name" : "readspec",
				"input" : {
					"devicetype" 	: "zwave",
					"id" 			: "ID 0",
					"class"			: "CONFIGURATION",
					"command"		: "GET",
					"type"			: "ONOFF_LED"
				}
			},
			{
				"name" : "writespec",
				"input" : {
					"devicetype" 	: "zwave",
					"id" 			: "ID 0",
					"class"			: "CONFIGURATION",
					"command"		: "SET",
					"data0"			: "ONOFF_LED",
					"data1"			: "1",
					"data2"			: ""
				}
			},
			{
				"name" : "readspec",
				"input" : {
					"devicetype" 	: "zwave",
					"id" 			: "ID 0",
					"class"			: "CONFIGURATION",
					"command"		: "GET",
					"type"			: "ONOFF_LED"
				}
			},
            {
                "name"              : "controlonoff",
                "input"             : {
                    "devicetype"    : "zwave",
                    "id"            : "ID 0",
                    "value"         : "1"
                }
            },
            {
                "name"              : "controlonoff",
                "input"             : {
                    "devicetype"    : "zwave",
                    "id"            : "ID 0",
                    "value"         : "0"
                }
            },
            {
                "name"              : "controlonoff",
                "input"             : {
                    "devicetype"    : "zwave",
                    "id"            : "ID 0",
                    "value"         : "30"
                }
            },
            {
                "name"              : "controlonoff",
                "input"             : {
                    "devicetype"    : "zwave",
                    "id"            : "ID 0",
                    "value"         : "63"
                }
            }		
		]
	}
]
